frago/__init__.py
frago/apps.py
frago/cli.py
frago/conf.py
frago/exceptions.py
frago/logger.py
frago/models.py
frago/serializers.py
frago/signals.py
frago/storage.py
frago/urls.py
frago/utils.py
frago/views.py
frago-0.1.4.dist-info/licenses/LICENSE
frago-0.1.4.dist-info/METADATA
frago-0.1.4.dist-info/WHEEL
frago-0.1.4.dist-info/entry_points.txt
frago-0.1.4.dist-info/top_level.txt
frago-0.1.4.dist-info/RECORD
