Metadata-Version: 2.4
Name: frago
Version: 0.1.4
Summary: Reusable Django app for resumable parallel chunked file uploads
Home-page: https://github.com/Albinm123/frago
Author: Albin Mathew
Author-email: Albin Mathew <albinm970@gmail.com>
License: MIT
Project-URL: Homepage, https://github.com/Albinm123/frago
Project-URL: Documentation, https://github.com/Albinm123/frago#readme
Project-URL: Source, https://github.com/Albinm123/frago
Project-URL: Tracker, https://github.com/Albinm123/frago/issues
Requires-Python: >=3.7
License-File: LICENSE
Requires-Dist: Django>=3.2
Requires-Dist: djangorestframework>=3.12
Dynamic: author
Dynamic: home-page
Dynamic: license-file
Dynamic: requires-python
